{
  "set": 110,
  "name": "SuperFlyers Sem2 Set 2",
  "grade": "SuperFlyers",
  "words": [
    {
      "word": "blogger",
      "hint": ""
    },
    {
      "word": "connection",
      "hint": ""
    },
    {
      "word": "data",
      "hint": ""
    },
    {
      "word": "upload",
      "hint": ""
    },
    {
      "word": "electronics",
      "hint": ""
    },
    {
      "word": "equipment",
      "hint": ""
    },
    {
      "word": "install",
      "hint": ""
    },
    {
      "word": "operator",
      "hint": ""
    },
    {
      "word": "server",
      "hint": ""
    },
    {
      "word": "sign up",
      "hint": ""
    },
    {
      "word": "souvenirs",
      "hint": ""
    },
    {
      "word": "go sightseeing",
      "hint": ""
    },
    {
      "word": "travel",
      "hint": ""
    },
    {
      "word": "journey",
      "hint": ""
    },
    {
      "word": "trip",
      "hint": ""
    }
  ]
}