{
  "set": 39,
  "name": "Starters Sem2 Set 16",
  "grade": "Starters",
  "words": [
    {
      "word": "karate class",
      "hint": ""
    },
    {
      "word": "dance class",
      "hint": ""
    },
    {
      "word": "swimming class",
      "hint": ""
    },
    {
      "word": "english class",
      "hint": ""
    },
    {
      "word": "brazil",
      "hint": ""
    },
    {
      "word": "canada",
      "hint": ""
    },
    {
      "word": "egypt",
      "hint": ""
    },
    {
      "word": "south korea",
      "hint": ""
    }
  ]
}